bin/__init__.py
bin/rouge.py
rouge_metric/__init__.py
rouge_metric/perl_cmd.py
rouge_metric/perl_rouge.py
rouge_metric/py_rouge.py
rouge_metric/RELEASE-1.5.5/README.txt
rouge_metric/RELEASE-1.5.5/RELEASE-NOTE.txt
rouge_metric/RELEASE-1.5.5/ROUGE-1.5.5.pl
rouge_metric/RELEASE-1.5.5/runROUGE-test.pl
rouge_metric/RELEASE-1.5.5/XML/DOM.pm
rouge_metric/RELEASE-1.5.5/XML/RegExp.pm
rouge_metric/RELEASE-1.5.5/XML/DOM/AttDef.pod
rouge_metric/RELEASE-1.5.5/XML/DOM/AttlistDecl.pod
rouge_metric/RELEASE-1.5.5/XML/DOM/Attr.pod
rouge_metric/RELEASE-1.5.5/XML/DOM/CDATASection.pod
rouge_metric/RELEASE-1.5.5/XML/DOM/CharacterData.pod
rouge_metric/RELEASE-1.5.5/XML/DOM/Comment.pod
rouge_metric/RELEASE-1.5.5/XML/DOM/DOMException.pm
rouge_metric/RELEASE-1.5.5/XML/DOM/DOMImplementation.pod
rouge_metric/RELEASE-1.5.5/XML/DOM/Document.pod
rouge_metric/RELEASE-1.5.5/XML/DOM/DocumentFragment.pod
rouge_metric/RELEASE-1.5.5/XML/DOM/DocumentType.pod
rouge_metric/RELEASE-1.5.5/XML/DOM/Element.pod
rouge_metric/RELEASE-1.5.5/XML/DOM/ElementDecl.pod
rouge_metric/RELEASE-1.5.5/XML/DOM/Entity.pod
rouge_metric/RELEASE-1.5.5/XML/DOM/EntityReference.pod
rouge_metric/RELEASE-1.5.5/XML/DOM/NamedNodeMap.pm
rouge_metric/RELEASE-1.5.5/XML/DOM/NamedNodeMap.pod
rouge_metric/RELEASE-1.5.5/XML/DOM/Node.pod
rouge_metric/RELEASE-1.5.5/XML/DOM/NodeList.pm
rouge_metric/RELEASE-1.5.5/XML/DOM/NodeList.pod
rouge_metric/RELEASE-1.5.5/XML/DOM/Notation.pod
rouge_metric/RELEASE-1.5.5/XML/DOM/Parser.pod
rouge_metric/RELEASE-1.5.5/XML/DOM/PerlSAX.pm
rouge_metric/RELEASE-1.5.5/XML/DOM/ProcessingInstruction.pod
rouge_metric/RELEASE-1.5.5/XML/DOM/Text.pod
rouge_metric/RELEASE-1.5.5/XML/DOM/XMLDecl.pod
rouge_metric/RELEASE-1.5.5/XML/Handler/BuildDOM.pm
rouge_metric/RELEASE-1.5.5/data/smart_common_words.txt
rouge_metric/RELEASE-1.5.5/data/WordNet-2.0-Exceptions/adj.exc
rouge_metric/RELEASE-1.5.5/data/WordNet-2.0-Exceptions/adv.exc
rouge_metric/RELEASE-1.5.5/data/WordNet-2.0-Exceptions/buildExeptionDB.pl
rouge_metric-1.0.1.dist-info/LICENSE
rouge_metric-1.0.1.dist-info/METADATA
rouge_metric-1.0.1.dist-info/WHEEL
rouge_metric-1.0.1.dist-info/entry_points.txt
rouge_metric-1.0.1.dist-info/top_level.txt
rouge_metric-1.0.1.dist-info/RECORD
