Metadata-Version: 2.1
Name: rouge-metric
Version: 1.0.1
Summary: A fast python implementation of full ROUGE metrics for automatic summarization.
Home-page: https://github.com/li-plus/rouge-metric
Author: Jiahao Li
Author-email: liplus17@163.com
Maintainer: Jiahao Li
Maintainer-email: liplus17@163.com
License: MIT
Keywords: rouge,summarization,natural language processing,computational linguistics
Platform: UNKNOWN
Classifier: Development Status :: 4 - Beta
Classifier: Intended Audience :: Science/Research
Classifier: Topic :: Text Processing :: Linguistic
Classifier: License :: OSI Approved :: MIT License
Classifier: Programming Language :: Python :: 2
Classifier: Programming Language :: Python :: 3
Requires-Python: >=2.7,!=3.0.*,!=3.1.*,!=3.2.*,!=3.3.*,!=3.4.*
Provides-Extra: dev
